celery_task_class/__init__.py
celery_task_class-0.1.0.dist-info/LICENSE
celery_task_class-0.1.0.dist-info/METADATA
celery_task_class-0.1.0.dist-info/WHEEL
celery_task_class-0.1.0.dist-info/RECORD
