Metadata-Version: 2.3
Name: celery-task-class
Version: 0.1.0
Summary: Write Celery task as a class
License: MIT
Author: Enrico Barzetti
Author-email: 7615875+enricobarzetti@users.noreply.github.com
Requires-Python: >=3.9
Classifier: License :: OSI Approved :: MIT License
Classifier: Programming Language :: Python :: 3
Classifier: Programming Language :: Python :: 3.9
Classifier: Programming Language :: Python :: 3.10
Classifier: Programming Language :: Python :: 3.11
Classifier: Programming Language :: Python :: 3.12
Classifier: Programming Language :: Python :: 3.13
Requires-Dist: celery (>=5.6.2,<6.0.0)
